LICENSE
MANIFEST.in
README.rst
requirements.txt
setup.py
dap2rpm/__init__.py
dap2rpm/dap.py
dap2rpm/exceptions.py
dap2rpm/files.template
dap2rpm/logger.py
dap2rpm/setup.py
dap2rpm/spec.template
dap2rpm.egg-info/PKG-INFO
dap2rpm.egg-info/SOURCES.txt
dap2rpm.egg-info/dependency_links.txt
dap2rpm.egg-info/entry_points.txt
dap2rpm.egg-info/requires.txt
dap2rpm.egg-info/top_level.txt