Metadata-Version: 1.1
Name: dap2rpm
Version: 0.1.11
Summary: Generate RPM specfile for DevAssistant DAP packages
Home-page: https://github.com/devassistant/dap2rpm
Author: Bohuslav Kabrda
Author-email: bkabrda@redhat.com
License: GPLv2
Keywords: DevAssistant,DAP,RPM,specfile
Platform: UNKNOWN
Classifier: Development Status :: 4 - Beta
Classifier: Intended Audience :: Developers
Classifier: License :: OSI Approved :: GNU General Public License v2 (GPLv2)
Classifier: Operating System :: POSIX :: Linux
Classifier: Programming Language :: Python
